loggerithm/__init__.py
loggerithm/handlers.py
loggerithm-1.1.1.dist-info/LICENSE.txt
loggerithm-1.1.1.dist-info/WHEEL
loggerithm-1.1.1.dist-info/METADATA
loggerithm-1.1.1.dist-info/RECORD
